bioreactor_model/__init__.py
bioreactor_model/bioreactor.py
bioreactor_model/calc.py
bioreactor_model-0.0.8.dist-info/METADATA
bioreactor_model-0.0.8.dist-info/WHEEL
bioreactor_model-0.0.8.dist-info/licenses/LICENSE
bioreactor_model-0.0.8.dist-info/RECORD
