Metadata-Version: 2.4
Name: bioreactor_model
Version: 0.0.8
Summary: Bioreactor-model is a Python package for bioreactor and biomass growth calculations
Project-URL: Homepage, https://asbldex.github.io
Project-URL: Documentation, https://matrixdex.github.io/bioreactor-model/
Project-URL: Issues, https://github.com/matrixdex/bioreactor-model/issues
Project-URL: Repository, https://github.com/matrixdex/bioreactor-model
Author-email: Noorul Ali <manonthemoon13131@gmail.com>
License-Expression: CC0-1.0
License-File: LICENSE
Classifier: License :: CC0 1.0 Universal (CC0 1.0) Public Domain Dedication
Classifier: Operating System :: OS Independent
Classifier: Programming Language :: Python :: 3
Requires-Python: >=3.13
Requires-Dist: numpy
